contract/__init__.py
contract/admin.py
contract/apps.py
contract/forms.py
contract/models.py
contract/signals.py
contract/tests.py
contract/urls.py
contract/urls_man.py
contract/views.py
contract/api/urls.py
contract/api/views.py
contract/api/__pycache__/urls.cpython-310.pyc
contract/api/__pycache__/urls.cpython-37.pyc
contract/api/__pycache__/views.cpython-310.pyc
contract/api/__pycache__/views.cpython-37.pyc
contract/forms/__init__.py
contract/forms/cont_form.py
contract/forms/man_form.py
contract/forms/__pycache__/__init__.cpython-310.pyc
contract/forms/__pycache__/__init__.cpython-37.pyc
contract/forms/__pycache__/__init__.cpython-39.pyc
contract/forms/__pycache__/cont_form.cpython-310.pyc
contract/forms/__pycache__/cont_form.cpython-37.pyc
contract/forms/__pycache__/cont_form.cpython-39.pyc
contract/forms/__pycache__/man_form.cpython-310.pyc
contract/forms/__pycache__/man_form.cpython-37.pyc
contract/forms/__pycache__/man_form.cpython-39.pyc
contract/migrations/0001_initial.py
contract/migrations/0002_rename_section_contract_department_and_more.py
contract/migrations/0003_rename_end_reason_empplacement_reason_and_more.py
contract/migrations/0004_remove_contract_category_remove_contract_de_and_more.py
contract/migrations/0005_empplacement_position_alter_empposition_department.py
contract/migrations/0006_remove_empsalary_employee_remove_empsalary_position.py
contract/migrations/0007_rename_total_empsalary_amount_and_more.py
contract/migrations/0008_empsalary_employee.py
contract/migrations/0009_alter_empsalary_datetime_alter_empsalary_hashed_and_more.py
contract/migrations/0010_category_is_dep_category_is_deputy_category_is_eng_and_more.py
contract/migrations/0011_category_is_advisor.py
contract/migrations/0012_remove_category_is_advisor_remove_category_is_dep_and_more.py
contract/migrations/0013_empposition_is_manager.py
contract/migrations/0014_alter_contract_file.py
contract/migrations/0015_organograma.py
contract/migrations/0016_alter_organograma_user.py
django_ipghrms_contract-1.17.dist-info/LICENSE
django_ipghrms_contract-1.17.dist-info/METADATA
django_ipghrms_contract-1.17.dist-info/WHEEL
django_ipghrms_contract-1.17.dist-info/top_level.txt
django_ipghrms_contract-1.17.dist-info/RECORD
